[
  {
    "imdb": "tt0072933",
    "title": "Emmanuelle II",
    "year": 1975,
    "genres": [
      "Drama",
      "Romance"
    ],
    "count": 13,
    "all_lines": 468,
    "occurrences": [
      [
        89,
        "00:16:20.860000",
        "00:16:24.409000",
        "No. Young miss here saved my life. -Young miss is actually Emmanuelle."
      ],
      [
        129,
        "00:20:21.460000",
        "00:20:25.079000",
        "You know my wife Emmanuelle? Emmanuelle. Laura."
      ],
      [
        135,
        "00:20:42.019000",
        "00:20:45.460000",
        "Tomorrow... bring Emmanuelle. -With pleasure, Madame."
      ],
      [
        252,
        "00:39:07.579000",
        "00:39:10.559000",
        "ls Emmanuelle OK? -Yes, she's fine."
      ],
      [
        256,
        "00:39:24.260000",
        "00:39:28.469000",
        "Emmanuelle does whatever she likes. -What ifyou see someone jump her?"
      ],
      [
        259,
        "00:39:38.659000",
        "00:39:41.570000",
        "Listen l have no claim on 'Emmanuelle."
      ],
      [
        302,
        "00:52:32.059000",
        "00:52:36.340000",
        "Nothing. l like Emmanuelle."
      ],
      [
        307,
        "00:52:58.099000",
        "00:53:01.510000",
        "l'll tell you something: l don't Iove Laura, l love Emmanuelle."
      ],
      [
        309,
        "00:53:05.500000",
        "00:53:09.500000",
        "lt's a risk l have to take, but l Iove risks, and so does Emmanuelle."
      ],
      [
        313,
        "00:53:26.019000",
        "00:53:30.340000",
        "l have no claim on Emmanuelle. Her pleasure is my pleasure."
      ],
      [
        413,
        "01:09:17.100000",
        "01:09:20.289000",
        "And Emmanuelle for her lectures in moralitty."
      ],
      [
        422,
        "01:10:29.020000",
        "01:10:32.989000",
        "Oh, Emmanuelle... -l didn't mean to wake you."
      ]
    ],
    "regex": "\\b((?!\\bEmmanuelle:)Emmanuelle)(?!\\:)(?!'t)\\b",
    "runtime": 83,
    "characters": [],
    "title_is_name": false,
    "rating": 4.8
  }
]
