[
  {
    "imdb": "tt0085295",
    "title": "Careful, He Might Hear You",
    "year": 1983,
    "genres": [
      "Drama"
    ],
    "count": 1,
    "all_lines": 1477,
    "occurrences": [
      [
        19,
        "00:02:34.670000",
        "00:02:37.411000",
        "- Careful, he might hear you."
      ]
    ],
    "regex": "\\b((?!\\bCareful,\\ He\\ Might\\ Hear\\ You:)Careful,\\ He\\ Might\\ Hear\\ You)(?!\\:)(?!'t)\\b",
    "runtime": 110,
    "characters": [],
    "title_is_name": false,
    "rating": 6.9
  }
]
