[
  {
    "imdb": "tt0084237",
    "title": "The Last Unicorn",
    "year": 1982,
    "genres": [
      "Adventure",
      "Animation",
      "Drama"
    ],
    "count": 7,
    "all_lines": 860,
    "occurrences": [
      [
        17,
        "00:03:02.880000",
        "00:03:10.960000",
        "They will stare, unbelieving, at the last unicorn..."
      ],
      [
        21,
        "00:03:43.100000",
        "00:03:51.920000",
        "In the distance, hear the laughter of the last unicorn!"
      ],
      [
        27,
        "00:04:37.080000",
        "00:04:45.910000",
        "Look and see her, how she sparkles, it's the last unicorn!"
      ],
      [
        383,
        "00:39:34.340000",
        "00:39:36.150000",
        "She's the last unicorn in the world."
      ],
      [
        384,
        "00:39:36.780000",
        "00:39:40.280000",
        "It would be the last unicorn in the wourld that came to Molly Grue."
      ],
      [
        394,
        "00:40:13.970000",
        "00:40:17.840000",
        "What were you going to do with the last unicorn in the world - keep her in a cage?"
      ],
      [
        856,
        "01:28:03.680000",
        "01:28:12.470000",
        "Look and see her, how she sparkles, it's the last unicorn!"
      ]
    ],
    "regex": "\\b((?!\\bLast\\ Unicorn:)Last\\ Unicorn)(?!\\:)(?!'t)\\b",
    "runtime": 92,
    "characters": [],
    "title_is_name": false,
    "rating": 7.3
  }
]
