[
  {
    "imdb": "tt0092615",
    "title": "The Barbarians",
    "year": 1987,
    "genres": [
      "Action",
      "Adventure",
      "Fantasy"
    ],
    "count": 1,
    "all_lines": 755,
    "occurrences": [
      [
        161,
        "00:21:31.599000",
        "00:21:35.403000",
        "But not ordinary men... barbarians."
      ]
    ],
    "regex": "\\b((?!\\bBarbarians:)Barbarians)(?!\\:)(?!'t)\\b",
    "runtime": 87,
    "characters": [],
    "title_is_name": false,
    "rating": 5
  }
]
