[
  {
    "imdb": "tt0076147",
    "title": "Hitler: A Film from Germany",
    "year": 1977,
    "genres": [
      "Biography",
      "Drama"
    ],
    "count": 22,
    "all_lines": 586,
    "occurrences": [
      [
        34,
        "00:13:56.577000",
        "00:13:59.447000",
        "(Hitler, 1932)"
      ],
      [
        35,
        "00:14:05.086000",
        "00:14:08.756000",
        "Hitler A Film from Germany"
      ],
      [
        98,
        "00:19:37.455000",
        "00:19:42.927000",
        "Who does the world hold guilty? And what would Hitler be without us?"
      ],
      [
        151,
        "00:25:45.860000",
        "00:25:49.730000",
        "We're in between Jesus and Hitler"
      ],
      [
        180,
        "00:29:29.852000",
        "00:29:34.324000",
        "That Valentin did not sell his famous collection of postcards to Adolf Hitler"
      ],
      [
        184,
        "00:29:49.038000",
        "00:29:53.209000",
        "...because Hitler demanded he should stop making films"
      ],
      [
        190,
        "00:30:24.908000",
        "00:30:29.045000",
        "Weeping after Hitler had gone, that was our Valentin"
      ],
      [
        192,
        "00:30:35.452000",
        "00:30:42.192000",
        "The people after Hitler had no more use for that Valentin"
      ],
      [
        202,
        "00:31:43.320000",
        "00:31:47.491000",
        "We march on for Hitler, through night and danger"
      ],
      [
        217,
        "00:33:37.569000",
        "00:33:41.406000",
        "As we have no Hitler to exhibit in a cage..."
      ],
      [
        223,
        "00:34:04.429000",
        "00:34:08.300000",
        "...acts here, in front of all, his own version of Hitler..."
      ],
      [
        241,
        "00:35:35.955000",
        "00:35:39.492000",
        "It's about the Hitler within us..."
      ],
      [
        254,
        "00:37:31.805000",
        "00:37:36.277000",
        "Germany is Hitler! Hitler is Germany!"
      ],
      [
        263,
        "00:38:15.016000",
        "00:38:18.219000",
        "(Hitler, Vienna, 1938)"
      ],
      [
        407,
        "00:58:23.602000",
        "00:58:27.139000",
        "...finally only as an aged Hitler..."
      ],
      [
        429,
        "01:00:12.712000",
        "01:00:18.151000",
        "...before this man, created in God's image, even he? Hitler like us"
      ],
      [
        442,
        "01:01:46.139000",
        "01:01:49.009000",
        "(Hitler, Reichstag, 19th July, 1942)"
      ],
      [
        515,
        "01:09:45.690000",
        "01:09:49.861000",
        "The clown as Hitler in us"
      ],
      [
        519,
        "01:10:04.876000",
        "01:10:10.315000",
        "The Hitler of the simple man in the street, that's me"
      ],
      [
        560,
        "01:13:30.016000",
        "01:13:32.886000",
        "This is about the Hitler of the simple man"
      ]
    ],
    "regex": "\\b((?!\\bHitler:)Hitler|(?!\\bFilm\\ from\\ Germany:)Film\\ from\\ Germany)(?!\\:)(?!'t)\\b",
    "runtime": 442,
    "characters": [],
    "title_is_name": false,
    "rating": 7.5
  }
]
