[
  {
    "imdb": "tt0168501",
    "title": "The Best Man",
    "year": 1999,
    "genres": [
      "Comedy",
      "Drama",
      "Romance"
    ],
    "count": 7,
    "all_lines": 1533,
    "occurrences": [
      [
        168,
        "00:13:51.751000",
        "00:13:55.450000",
        "Yes, indeed. That is Harper Stewart, Lance Sullivan's best man."
      ],
      [
        265,
        "00:20:42.442000",
        "00:20:45.015000",
        "The best man is here. I'm gonna hook you up."
      ],
      [
        872,
        "00:58:05.898000",
        "00:58:07.854000",
        "the best man, Harper Stewart."
      ],
      [
        963,
        "01:04:39.758000",
        "01:04:42.131000",
        "Best man's gotta carry the rings and the vows."
      ],
      [
        1001,
        "01:07:23.822000",
        "01:07:26.313000",
        "That is my best man, Mr. Harper Stewart."
      ],
      [
        1349,
        "01:34:11.170000",
        "01:34:13.247000",
        "Mia slept with your best man."
      ],
      [
        1506,
        "01:51:05.962000",
        "01:51:09.248000",
        "And besides I think the best man over there needs you."
      ]
    ],
    "regex": "\\b((?!\\bBest\\ Man:)Best\\ Man)(?!\\:)(?!'t)\\b",
    "runtime": 120,
    "characters": [],
    "title_is_name": false,
    "rating": 6.7
  }
]
