[
  {
    "imdb": "tt0122143",
    "title": "The Last Broadcast",
    "year": 1998,
    "genres": [
      "Horror",
      "Mystery"
    ],
    "count": 1,
    "all_lines": 869,
    "occurrences": [
      [
        487,
        "00:39:25.599000",
        "00:39:31.663000",
        "At 10PM in what will be, The Last Broadcast, Fact or Fiction goes live."
      ]
    ],
    "regex": "\\b((?!\\bLast\\ Broadcast:)Last\\ Broadcast)(?!\\:)(?!'t)\\b",
    "runtime": 86,
    "characters": [],
    "title_is_name": false,
    "rating": 5.2
  }
]
