[
  {
    "imdb": "tt0123188",
    "title": "Nemuri Kyôshirô: Joyôken",
    "year": 1964,
    "genres": [
      "Action",
      "Drama"
    ],
    "count": 10,
    "all_lines": 656,
    "occurrences": [
      [
        1,
        "00:00:13.613000",
        "00:00:21.884000",
        "Nemuri Kyoshiro: Joyoken Nemuri Kyoshiro: She-Devil Slaying Sword Sleepy Eyes of Death: Sword of Seduction"
      ],
      [
        6,
        "00:00:38.138000",
        "00:00:40.572000",
        "Ichikawa Raizo as Nemuri Kyoshiro"
      ],
      [
        29,
        "00:04:26.733000",
        "00:04:28.701000",
        "You are Sir Nemuri Kyoshiro, are you not?"
      ],
      [
        229,
        "00:26:00.592000",
        "00:26:04.426000",
        "Please inform him that Nemuri Kyoshiro stopped by to return his medicine box."
      ],
      [
        270,
        "00:29:50.155000",
        "00:29:53.124000",
        "I'm an unworthy being... Nemuri Kyoshiro."
      ],
      [
        409,
        "00:49:37.341000",
        "00:49:39.400000",
        "You must be Sir Nemuri Kyoshiro."
      ],
      [
        484,
        "00:57:06.489000",
        "00:57:11.654000",
        "Nemuri Kyoshiro... please leave our territory at once."
      ],
      [
        528,
        "01:02:49.632000",
        "01:02:52.396000",
        "My name is Nemuri Kyoshiro."
      ],
      [
        561,
        "01:08:13.789000",
        "01:08:16.223000",
        "Welcome, Nemuri Kyoshiro..."
      ],
      [
        644,
        "01:18:14.289000",
        "01:18:17.554000",
        "You are that child... Nemuri Kyoshiro!"
      ]
    ],
    "regex": "\\b((?!\\bNemuri\\ Kyoshiro:)Nemuri\\ Kyoshiro|(?!\\bJoyoken:)Joyoken)(?!\\:)(?!'t)\\b",
    "runtime": 87,
    "characters": [],
    "title_is_name": false,
    "rating": 6.9
  }
]
