[
  {
    "imdb": "tt0104181",
    "title": "Wuthering Heights",
    "year": 1992,
    "genres": [
      "Drama",
      "History",
      "Romance"
    ],
    "count": 9,
    "all_lines": 1107,
    "occurrences": [
      [
        46,
        "00:08:24.723000",
        "00:08:27.309000",
        "when an old man returned to Wuthering Heights..."
      ],
      [
        417,
        "00:36:24.942000",
        "00:36:28.139000",
        "Cathy turned away from her old life at Wuthering Heights."
      ],
      [
        474,
        "00:41:25.275000",
        "00:41:27.163000",
        "At Wuthering Heights."
      ],
      [
        477,
        "00:41:30.236000",
        "00:41:32.506000",
        "at Wuthering Heights?"
      ],
      [
        483,
        "00:41:48.063000",
        "00:41:50.551000",
        "I am the owner of Wuthering Heights now."
      ],
      [
        816,
        "01:08:49.988000",
        "01:08:53.021000",
        "Why do you forbid me to visit Wuthering Heights?"
      ],
      [
        841,
        "01:10:43.170000",
        "01:10:47.261000",
        "has forbidden you to visit Wuthering Heights."
      ],
      [
        946,
        "01:20:57.273000",
        "01:21:01.680000",
        "I've come to fetch you home to Wuthering Heights."
      ],
      [
        1048,
        "01:30:32.975000",
        "01:30:35.495000",
        "He's robbed you of Wuthering Heights."
      ]
    ],
    "regex": "\\b((?!\\bWuthering\\ Heights:)Wuthering\\ Heights)(?!\\:)(?!'t)\\b",
    "runtime": 105,
    "characters": [],
    "title_is_name": false,
    "rating": 6.6
  }
]
