[
  {
    "imdb": "tt0314331",
    "title": "Love Actually",
    "year": 2003,
    "genres": [
      "Comedy",
      "Drama",
      "Romance"
    ],
    "count": 1,
    "all_lines": 1763,
    "occurrences": [
      [
        11,
        "00:01:49.070000",
        "00:01:55.500000",
        "'lf you look for it, I've got a sneaky feeling you'll find that love actually is all around.'"
      ]
    ],
    "regex": "\\b((?!\\bLove\\ Actually:)Love\\ Actually)(?!\\:)(?!'t)\\b",
    "runtime": 135,
    "characters": [],
    "title_is_name": false,
    "rating": 7.6
  }
]
