[
  {
    "imdb": "tt0923923",
    "title": "Happy Birthday",
    "year": 2007,
    "genres": [
      "Romance"
    ],
    "count": 20,
    "all_lines": 1086,
    "occurrences": [
      [
        1,
        "00:00:13.546000",
        "00:00:18.381000",
        "Happy birthday to you..."
      ],
      [
        2,
        "00:00:18.451000",
        "00:00:22.820000",
        "happy birthday to Mi!"
      ],
      [
        18,
        "00:00:55.622000",
        "00:00:56.987000",
        "Happy Birthday!"
      ],
      [
        21,
        "00:01:10.403000",
        "00:01:13.167000",
        "Wish Mi Happy Birthday for me"
      ],
      [
        34,
        "00:03:41.588000",
        "00:03:43.146000",
        "Happy Birthday"
      ],
      [
        35,
        "00:03:50.563000",
        "00:03:53.760000",
        "\"Happy Birthday\""
      ],
      [
        47,
        "00:05:25.525000",
        "00:05:26.719000",
        "Happy birthday"
      ],
      [
        49,
        "00:05:29.762000",
        "00:05:35.730000",
        "Happy birthday to you"
      ],
      [
        50,
        "00:05:35.802000",
        "00:05:40.762000",
        "Happy birthday to Mi..."
      ],
      [
        51,
        "00:05:40.840000",
        "00:05:46.278000",
        "Happy birthday to you!"
      ],
      [
        75,
        "00:07:17.270000",
        "00:07:19.795000",
        "he hasn't said Happy Birthday to me"
      ],
      [
        436,
        "00:39:23.094000",
        "00:39:26.586000",
        "Happy birthday to you"
      ],
      [
        437,
        "00:39:26.697000",
        "00:39:30.064000",
        "Happy birthday to Mi..."
      ],
      [
        634,
        "00:56:38.562000",
        "00:56:45.766000",
        "Happy birthday to you"
      ],
      [
        635,
        "00:56:45.836000",
        "00:56:50.705000",
        "Happy birthday to you..."
      ],
      [
        636,
        "00:56:50.774000",
        "00:56:55.143000",
        "Happy birthday to Mi!"
      ],
      [
        641,
        "00:57:07.424000",
        "00:57:23.034000",
        "Happy birthday to you Happy birthday to me"
      ],
      [
        980,
        "01:32:56.538000",
        "01:32:59.598000",
        "Today's my birthday let me have a happy birthday"
      ],
      [
        985,
        "01:33:55.663000",
        "01:33:58.325000",
        "(Happy Birthday. Nam Forever)"
      ]
    ],
    "regex": "\\b((?!\\bHappy\\ Birthday:)Happy\\ Birthday)(?!\\:)(?!'t)\\b",
    "runtime": 107,
    "characters": [],
    "title_is_name": false,
    "rating": 6.4
  }
]
