[
  {
    "imdb": "tt11127878",
    "title": "Milea",
    "year": 2020,
    "genres": [
      "Drama",
      "Romance"
    ],
    "count": 20,
    "all_lines": 1431,
    "occurrences": [
      [
        95,
        "00:06:01.917000",
        "00:06:04.125000",
        "-What new girl? -Her name is Milea."
      ],
      [
        137,
        "00:09:02.208000",
        "00:09:03.333000",
        "Milea, I think."
      ],
      [
        138,
        "00:09:03.667000",
        "00:09:07.417000",
        "Milea. I think I saw her once. She's cute."
      ],
      [
        161,
        "00:10:56.083000",
        "00:10:57.667000",
        "Are you Milea?"
      ],
      [
        167,
        "00:11:13",
        "00:11:15.042000",
        "Milea Adnan Hussain."
      ],
      [
        169,
        "00:11:18.708000",
        "00:11:21.042000",
        "Milea, you're beautiful."
      ],
      [
        178,
        "00:11:46.667000",
        "00:11:47.833000",
        "Read it, Milea!"
      ],
      [
        192,
        "00:12:38.750000",
        "00:12:41.583000",
        "The school cafeteria sent me to inform Milea"
      ],
      [
        199,
        "00:13:00.708000",
        "00:13:03.250000",
        "-Can I talk to Milea? -Sure, Milea speaking."
      ],
      [
        214,
        "00:13:44.625000",
        "00:13:45.792000",
        "Happy birthday, Milea."
      ],
      [
        217,
        "00:13:55.583000",
        "00:13:59.125000",
        "Milea, Dilan wishes you a happy birthday."
      ],
      [
        221,
        "00:14:11.958000",
        "00:14:15.167000",
        "Happy birthday, Milea. Here's your gift."
      ],
      [
        226,
        "00:14:24.125000",
        "00:14:25.958000",
        "- Milea. - Yes, Dilan?"
      ],
      [
        268,
        "00:17:15.625000",
        "00:17:17.958000",
        "-Where's Milea? -No idea."
      ],
      [
        285,
        "00:19:03.375000",
        "00:19:05.750000",
        "It's Dilan. Is Milea there?"
      ],
      [
        309,
        "00:20:44.375000",
        "00:20:46",
        "Have you heard about Milea?"
      ],
      [
        1327,
        "01:31:22.208000",
        "01:31:24.667000",
        "-I'm Dilan. -Milea."
      ],
      [
        1379,
        "01:35:30.125000",
        "01:35:35.125000",
        "I was so lucky to get to know her, Milea Adnan Hussain."
      ],
      [
        1399,
        "01:36:46.625000",
        "01:36:50.583000",
        "Thank you, Lia. Milea Adnan Hussain."
      ]
    ],
    "regex": "\\b((?!\\bMilea:)Milea)(?!\\:)(?!'t)\\b",
    "runtime": 102,
    "characters": [
      "Milea"
    ],
    "title_is_name": true,
    "rating": 6.2
  }
]
