[
  {
    "imdb": "tt13617580",
    "title": "Zalava",
    "year": 2021,
    "genres": [
      "Drama",
      "Horror"
    ],
    "count": 12,
    "all_lines": 689,
    "occurrences": [
      [
        4,
        "00:01:36.592000",
        "00:01:40.800000",
        "...located in Zalava where they are local customs and rituals."
      ],
      [
        15,
        "00:04:32.592000",
        "00:04:37.092000",
        "'Considering the complaint from the residents of Zalava..."
      ],
      [
        20,
        "00:04:54.633000",
        "00:04:59.508000",
        "...Sergeant Massoud Ahmadi, head of the gendarmerie of Zalava..."
      ],
      [
        51,
        "00:07:51.050000",
        "00:07:55.175000",
        "Well in Nourabad. The mule carries it. The tests in Zalava are not finished yet."
      ],
      [
        65,
        "00:09:48.300000",
        "00:09:52.800000",
        "Hey, sergeant. Demons have attacked Zalava."
      ],
      [
        67,
        "00:09:56.925000",
        "00:09:59.717000",
        "Demons have attacked Zalava."
      ],
      [
        70,
        "00:10:04.842000",
        "00:10:06.300000",
        "There is a demon in Zalava."
      ],
      [
        75,
        "00:10:18.800000",
        "00:10:21.342000",
        "No. He goes to the doctor in Zalava."
      ],
      [
        249,
        "00:33:37.092000",
        "00:33:41.175000",
        "Amirza came a year and a half ago perform an exorcism in Zalava."
      ],
      [
        332,
        "00:47:16.300000",
        "00:47:18.258000",
        "Make that way searched for Zalava."
      ],
      [
        344,
        "00:48:07.800000",
        "00:48:11.133000",
        "Come with me. I go to the road towards Zalava."
      ],
      [
        385,
        "00:52:59.633000",
        "00:53:02.050000",
        "...but there was a problem with those from Zalava."
      ]
    ],
    "regex": "\\b((?!\\bZalava:)Zalava)(?!\\:)(?!'t)\\b",
    "runtime": 93,
    "characters": [],
    "title_is_name": false,
    "rating": 6.2
  }
]
