[
  {
    "imdb": "tt15766352",
    "title": "Randy Rhoads: Reflections of a Guitar Icon",
    "year": 2022,
    "genres": [
      "Documentary"
    ],
    "count": 20,
    "all_lines": 1577,
    "occurrences": [
      [
        10,
        "00:00:37.454000",
        "00:00:39.706000",
        "He was Randy Rhoads! (crowd cheering)"
      ],
      [
        20,
        "00:01:15.867000",
        "00:01:17.661000",
        "Randy Rhoads and his band,"
      ],
      [
        511,
        "00:27:25.727000",
        "00:27:27.938000",
        "and they have this guitar player named Randy Rhoads,"
      ],
      [
        520,
        "00:27:56.258000",
        "00:27:58.468000",
        "and wanting to see Randy Rhoads play again"
      ],
      [
        539,
        "00:28:54.858000",
        "00:28:59.279000",
        "-- Every night, Kevin would basically introduce Randy Rhoads"
      ],
      [
        543,
        "00:29:07.663000",
        "00:29:12.751000",
        "Like the incredible Randy Rhoads"
      ],
      [
        591,
        "00:34:42.831000",
        "00:34:44.749000",
        "and there's Randy Rhoads. Even before he was a huge star,"
      ],
      [
        596,
        "00:34:54.426000",
        "00:34:57.887000",
        "On lead guitar, this is Randy Rhoads!"
      ],
      [
        621,
        "00:36:31.022000",
        "00:36:34.567000",
        "and everybody's comparing Eddie Van Halen to Randy Rhoads."
      ],
      [
        622,
        "00:36:34.943000",
        "00:36:36.486000",
        "- Did you know Randy Rhoads?"
      ],
      [
        868,
        "00:48:52.638000",
        "00:48:54.223000",
        "- Guitarist Randy Rhoads."
      ],
      [
        873,
        "00:49:09.947000",
        "00:49:12.241000",
        "guitarist Randy Rhoads. -- (crowd cheering)"
      ],
      [
        1032,
        "00:55:50.138000",
        "00:55:51.431000",
        "but for Randy Rhoads,"
      ],
      [
        1056,
        "00:57:30.155000",
        "00:57:33.617000",
        "-- I was calling Randy Rhoads at his mother's music studio"
      ],
      [
        1084,
        "00:59:09.588000",
        "00:59:13.050000",
        "This guy introduced me to Randy Rhoads."
      ],
      [
        1227,
        "01:07:30.964000",
        "01:07:33.299000",
        "and Randy Rhoads on guitar."
      ],
      [
        1526,
        "01:24:51.128000",
        "01:24:52.796000",
        "that have guaranteed Randy Rhoads"
      ],
      [
        1531,
        "01:25:08.145000",
        "01:25:09.688000",
        "that I played with Randy Rhoads,"
      ],
      [
        1533,
        "01:25:14.776000",
        "01:25:17.654000",
        "but what all I can say about my memory of Randy Rhoads"
      ],
      [
        1539,
        "01:25:34.588000",
        "01:25:38.508000",
        "God bless Randy Rhoads. (crowd applauding)"
      ]
    ],
    "regex": "\\b((?!\\bRandy\\ Rhoads:)Randy\\ Rhoads|(?!\\bReflections\\ of\\ a\\ Guitar\\ Icon:)Reflections\\ of\\ a\\ Guitar\\ Icon)(?!\\:)(?!'t)\\b",
    "runtime": 89,
    "characters": [],
    "title_is_name": false,
    "rating": 7.1
  }
]
