[
  {
    "imdb": "tt2041321",
    "title": "Bunohan: Return to Murder",
    "year": 2011,
    "genres": [
      "Action",
      "Drama",
      "Thriller"
    ],
    "count": 6,
    "all_lines": 692,
    "occurrences": [
      [
        84,
        "00:12:36.280000",
        "00:12:40.273000",
        "Bunohan."
      ],
      [
        85,
        "00:13:13.400000",
        "00:13:16.472000",
        "Bunohan. Bunohan."
      ],
      [
        86,
        "00:13:20.440000",
        "00:13:22.317000",
        "Bunohan"
      ],
      [
        420,
        "00:55:45.360000",
        "00:55:49.353000",
        "Our very own champion, Adil Bunga Lalang from Bunohan."
      ],
      [
        448,
        "01:01:04.360000",
        "01:01:07.440000",
        "Brother, we made history in Bunohan."
      ]
    ],
    "regex": "\\b((?!\\bBunohan:)Bunohan|(?!\\bReturn\\ to\\ Murder:)Return\\ to\\ Murder)(?!\\:)(?!'t)\\b",
    "runtime": 97,
    "characters": [],
    "title_is_name": false,
    "rating": 6
  }
]
