[
  {
    "imdb": "tt3282088",
    "title": "Idukki Gold",
    "year": 2013,
    "genres": [
      "Comedy",
      "Drama"
    ],
    "count": 4,
    "all_lines": 1133,
    "occurrences": [
      [
        682,
        "01:07:50.960000",
        "01:07:52.600000",
        "and smoke Idukki Gold."
      ],
      [
        742,
        "01:12:40.640000",
        "01:12:41.960000",
        "What about Idukki Gold?"
      ],
      [
        843,
        "01:22:41.640000",
        "01:22:46.600000",
        "'Chapter Five, Idukki Gold.'"
      ],
      [
        865,
        "01:24:36.680000",
        "01:24:38.080000",
        "Idukki Gold."
      ]
    ],
    "regex": "\\b((?!\\bIdukki\\ Gold:)Idukki\\ Gold)(?!\\:)(?!'t)\\b",
    "runtime": 119,
    "characters": [],
    "title_is_name": false,
    "rating": 6.4
  }
]
