[
  {
    "imdb": "tt5463162",
    "title": "Deadpool 2",
    "year": 2018,
    "genres": [
      "Action",
      "Adventure",
      "Comedy"
    ],
    "count": 15,
    "all_lines": 2151,
    "occurrences": [
      [
        22,
        "00:02:56.530000",
        "00:02:58.406000",
        "DEADPOOL.: Hey, it's Gail calling."
      ],
      [
        566,
        "00:30:20.213000",
        "00:30:22.590000",
        "My name is DEADPOOL, and I'm an X-Man."
      ],
      [
        976,
        "00:54:00.174000",
        "00:54:01.175000",
        "DEADPOOL.: I like that."
      ],
      [
        1082,
        "00:57:59.371000",
        "00:58:00.413000",
        "DEADPOOL.: You all know the plan."
      ],
      [
        1086,
        "00:58:05.502000",
        "00:58:06.586000",
        "I wouldn't fuck with DEADPOOL either."
      ],
      [
        1283,
        "01:08:14.235000",
        "01:08:15.486000",
        "(DEADPOOL GASPS)"
      ],
      [
        1309,
        "01:10:07.348000",
        "01:10:08.849000",
        "DEADPOOL.: I'll be first to admit..."
      ],
      [
        1345,
        "01:11:55.581000",
        "01:11:57.624000",
        "(DEADPOOL SCREAMING)"
      ],
      [
        1577,
        "01:21:04.296000",
        "01:21:05.463000",
        "DEADPOOL.: You said it yourself."
      ],
      [
        1681,
        "01:25:19.384000",
        "01:25:20.760000",
        "(DEADPOOL SIGHS)"
      ],
      [
        1716,
        "01:28:17.854000",
        "01:28:18.855000",
        "(DEADPOOL GROANS)"
      ],
      [
        1844,
        "01:35:31.246000",
        "01:35:32.455000",
        "(DEADPOOL GROANS)"
      ],
      [
        1867,
        "01:37:01.878000",
        "01:37:03.379000",
        "(DEADPOOL COUGHING)"
      ],
      [
        2020,
        "01:45:58.122000",
        "01:45:59.706000",
        "(DEADPOOL GROANS)"
      ],
      [
        2056,
        "01:47:23.207000",
        "01:47:24.416000",
        "(DEADPOOL GROANS)"
      ]
    ],
    "regex": "\\b((?!\\bDeadpool:)Deadpool)(?!\\:)(?!'t)\\b",
    "runtime": 119,
    "characters": [],
    "title_is_name": false,
    "rating": 7.6
  }
]
