[
  {
    "imdb": "tt6244876",
    "title": "Honey Bee 2: Celebrations",
    "year": 2017,
    "genres": [
      "Comedy"
    ],
    "count": 2,
    "all_lines": 2833,
    "occurrences": [
      [
        62,
        "00:06:38.267000",
        "00:06:39.473000",
        "Honey Bee!"
      ],
      [
        75,
        "00:07:16.567000",
        "00:07:19.548000",
        "Whatever said &done, Honey Bee is in a different league altogether, bro!"
      ]
    ],
    "regex": "\\b((?!\\bHoney\\ Bee:)Honey\\ Bee|(?!\\bCelebrations:)Celebrations)(?!\\:)(?!'t)\\b",
    "runtime": 138,
    "characters": [],
    "title_is_name": false,
    "rating": 3.5
  }
]
